package_psycopg/__init__.py
package_psycopg/create_pool_psycopg2.py
package_psycopg/query_psycopg2.py
delameta_response_query_new-0.0.4.dist-info/METADATA
delameta_response_query_new-0.0.4.dist-info/WHEEL
delameta_response_query_new-0.0.4.dist-info/RECORD
